jsonrest/__init__.py
vti_jsonrest-1.0.2.dist-info/LICENSE
vti_jsonrest-1.0.2.dist-info/METADATA
vti_jsonrest-1.0.2.dist-info/WHEEL
vti_jsonrest-1.0.2.dist-info/top_level.txt
vti_jsonrest-1.0.2.dist-info/RECORD
