Metadata-Version: 2.1
Name: vti-jsonrest
Version: 1.0.2
Summary: A client library for discoverable REST APIs using JSON payloads.
Author: James Jurack
Author-email: James Jurack <james.jurack@ametek.com>
Project-URL: Homepage, https://github.com/VTI-Ametek/jsonrest
Project-URL: Documentation, https://jsonrest.readthedocs.io/
Classifier: Intended Audience :: Developers
Classifier: Natural Language :: English
Classifier: License :: OSI Approved :: Apache Software License
Classifier: Operating System :: OS Independent
Classifier: Development Status :: 5 - Production/Stable
Classifier: Programming Language :: Python
Classifier: Programming Language :: Python :: 2
Classifier: Programming Language :: Python :: 2.7
Classifier: Programming Language :: Python :: 3
Classifier: Programming Language :: Python :: 3.6
Classifier: Programming Language :: Python :: 3.7
Classifier: Programming Language :: Python :: 3.8
Classifier: Programming Language :: Python :: 3.9
Classifier: Programming Language :: Python :: 3.10
Classifier: Programming Language :: Python :: 3.11
Requires-Python: >=2.7
License-File: LICENSE
Requires-Dist: requests
